monarch_mcp_server/__init__.py
monarch_mcp_server/server.py
mseep_monarch_mcp_server-0.1.1.dist-info/licenses/LICENSE
mseep_monarch_mcp_server-0.1.1.dist-info/METADATA
mseep_monarch_mcp_server-0.1.1.dist-info/WHEEL
mseep_monarch_mcp_server-0.1.1.dist-info/entry_points.txt
mseep_monarch_mcp_server-0.1.1.dist-info/top_level.txt
mseep_monarch_mcp_server-0.1.1.dist-info/RECORD
