Metadata-Version: 2.4
Name: mseep-monarch-mcp-server
Version: 0.1.1
Summary: Model Context Protocol (MCP) server for Monarch Money personal finance platform
Author-email: mseep <support@skydeck.ai>
License: MIT
Project-URL: Homepage, https://github.com/robcerda/monarch-mcp-server
Project-URL: Repository, https://github.com/robcerda/monarch-mcp-server
Project-URL: Issues, https://github.com/robcerda/monarch-mcp-server/issues
Classifier: Development Status :: 3 - Alpha
Classifier: Intended Audience :: Developers
Classifier: License :: OSI Approved :: MIT License
Classifier: Programming Language :: Python :: 3
Classifier: Programming Language :: Python :: 3.12
Requires-Python: >=3.12
License-File: LICENSE
Requires-Dist: mcp[cli]>=1.0.0
Requires-Dist: monarchmoney>=0.1.12
Requires-Dist: python-dotenv>=1.0.0
Requires-Dist: pydantic>=2.0.0
Requires-Dist: asyncio>=3.4.3
Provides-Extra: dev
Requires-Dist: pytest>=7.0.0; extra == "dev"
Requires-Dist: pytest-asyncio>=0.21.0; extra == "dev"
Requires-Dist: black>=23.0.0; extra == "dev"
Requires-Dist: isort>=5.12.0; extra == "dev"
Requires-Dist: mypy>=1.0.0; extra == "dev"
Requires-Dist: pre-commit>=3.0.0; extra == "dev"
Dynamic: license-file
